toapigdc/__init__.py
toapigdc/toapigdc.py
toapigdc-1.0.1.dist-info/METADATA
toapigdc-1.0.1.dist-info/WHEEL
toapigdc-1.0.1.dist-info/RECORD
